kognitos/bdk/__version__.py
kognitos/bdk/api/__init__.py
kognitos/bdk/api/discoverable.py
kognitos/bdk/api/errors.py
kognitos/bdk/api/filter.py
kognitos/bdk/api/filter_visitor.py
kognitos/bdk/api/http_request.py
kognitos/bdk/api/http_response.py
kognitos/bdk/api/noun_phrase.py
kognitos/bdk/api/promise.py
kognitos/bdk/api/questions.py
kognitos/bdk/api/remote_io.py
kognitos/bdk/api/trigger_response.py
kognitos/bdk/api/user_info.py
kognitos/bdk/blueprints/__init__.py
kognitos/bdk/blueprints/file_storage_blueprint.py
kognitos/bdk/decorators/__init__.py
kognitos/bdk/decorators/blueprint_decorator.py
kognitos/bdk/decorators/book_decorator.py
kognitos/bdk/decorators/concept_decorator.py
kognitos/bdk/decorators/config_decorator.py
kognitos/bdk/decorators/connect_decorator.py
kognitos/bdk/decorators/discover_decorator.py
kognitos/bdk/decorators/discoverables_decorator.py
kognitos/bdk/decorators/invoke_decorator.py
kognitos/bdk/decorators/oauth_decorator.py
kognitos/bdk/decorators/oauthtoken_decorator.py
kognitos/bdk/decorators/procedure_decorator.py
kognitos/bdk/decorators/promise_decorator.py
kognitos/bdk/decorators/rules/__init__.py
kognitos/bdk/decorators/rules/promise_rules.py
kognitos/bdk/decorators/rules/question_rules.py
kognitos/bdk/decorators/rules/trigger_rules.py
kognitos/bdk/decorators/search_hint_decorator.py
kognitos/bdk/decorators/trigger/__init__.py
kognitos/bdk/decorators/trigger/trigger_decorator.py
kognitos/bdk/decorators/trigger/trigger_event_decorator.py
kognitos/bdk/decorators/trigger/trigger_setup_function.py
kognitos/bdk/decorators/userinfo_decorator.py
kognitos/bdk/docstring/__init__.py
kognitos/bdk/docstring/docstring.py
kognitos/bdk/docstring/error.py
kognitos/bdk/docstring/example.py
kognitos/bdk/docstring/parser.py
kognitos/bdk/docstring/sections.py
kognitos/bdk/errors.py
kognitos/bdk/reflection/__init__.py
kognitos/bdk/reflection/authentication/__init__.py
kognitos/bdk/reflection/authentication/book_authentication_descriptor.py
kognitos_bdk_api-2.1.1.dist-info/LICENSE
kognitos_bdk_api-2.1.1.dist-info/METADATA
kognitos_bdk_api-2.1.1.dist-info/WHEEL
kognitos_bdk_api-2.1.1.dist-info/entry_points.txt
kognitos_bdk_api-2.1.1.dist-info/RECORD
