Metadata-Version: 2.1
Name: kognitos-bdk-api
Version: 2.1.1
Summary: Kognitos Book Development Kit
License: Proprietary
Author: Emiliano Lesende
Author-email: emiliano@kognitos.com
Requires-Python: >=3.11,<4.0
Classifier: License :: Other/Proprietary License
Classifier: Programming Language :: Python :: 3
Classifier: Programming Language :: Python :: 3.11
Classifier: Programming Language :: Python :: 3.12
Provides-Extra: attrs
Requires-Dist: attrs (>=24.2.0,<25.0.0) ; extra == "attrs"
Requires-Dist: docstring-parser (>=0.15,<0.16)
Requires-Dist: kognitos-bdk-klang (>=2.0.0,<3.0.0)
Requires-Dist: uritemplate (>=4.1.1,<5.0.0)
